youcanpay/__init__.py
youcanpay/client.py
youcanpay_sdk-0.1.0.dist-info/licenses/LICENSE
youcanpay_sdk-0.1.0.dist-info/METADATA
youcanpay_sdk-0.1.0.dist-info/WHEEL
youcanpay_sdk-0.1.0.dist-info/top_level.txt
youcanpay_sdk-0.1.0.dist-info/RECORD
