Metadata-Version: 2.4
Name: youcanpay-sdk
Version: 0.1.0
Summary: SDK for integrating YouCan Pay API with Python
Home-page: https://github.com/yassir-aea/youcanpay
Author: Yassir AIT EL AIZZI
Author-email: yassir.aitelaizzi@gmail.com
License: MIT
Project-URL: Homepage, https://github.com/yassir-aea/youcanpay
Classifier: Development Status :: 3 - Alpha
Classifier: Intended Audience :: Developers
Classifier: License :: OSI Approved :: MIT License
Classifier: Operating System :: OS Independent
Classifier: Programming Language :: Python :: 3
Classifier: Programming Language :: Python :: 3.6
Classifier: Programming Language :: Python :: 3.7
Classifier: Programming Language :: Python :: 3.8
Classifier: Programming Language :: Python :: 3.9
Classifier: Topic :: Software Development :: Libraries :: Python Modules
Requires-Python: >=3.6
License-File: LICENSE
Requires-Dist: requests>=2.25.1
Dynamic: author
Dynamic: author-email
Dynamic: classifier
Dynamic: description
Dynamic: description-content-type
Dynamic: home-page
Dynamic: license
Dynamic: license-file
Dynamic: project-url
Dynamic: requires-dist
Dynamic: requires-python
Dynamic: summary
